Metadata-Version: 2.1
Name: odoo-addon-l10n_es_vat_prorate
Version: 18.0.1.0.3
Requires-Python: >=3.10
Requires-Dist: odoo-addon-l10n_es_aeat==18.0.*
Requires-Dist: odoo==18.0.*
Summary: =?utf-8?q?Prorrata_de_IVA_para_la_localizaci=C3=B3n_espa=C3=B1ola?=
Home-page: https://github.com/OCA/l10n-spain
License: AGPL-3
Author: Creu Blanca, Tecnativa, Odoo Community Association (OCA)
Author-email: support@odoo-community.org
Classifier: Programming Language :: Python
Classifier: Framework :: Odoo
Classifier: Framework :: Odoo :: 18.0
Classifier: License :: OSI Approved :: GNU Affero General Public License v3
